emcie/common/__init__.py
emcie/common/base_models.py
emcie/common/plugin.py
emcie/common/py.typed
emcie/common/tools.py
emcie/common/types.py
emcie_common-0.1.0.dist-info/METADATA
emcie_common-0.1.0.dist-info/WHEEL
emcie_common-0.1.0.dist-info/RECORD
