Metadata-Version: 2.1
Name: emcie-common
Version: 0.1.0
Summary: 
Author: Yam Marcovitz
Author-email: yam@emcie.co
Requires-Python: >=3.12,<4.0
Classifier: Programming Language :: Python :: 3
Classifier: Programming Language :: Python :: 3.12
Requires-Dist: fastapi (>=0.112.0,<0.113.0)
Requires-Dist: uvicorn (>=0.30.5,<0.31.0)
